main.py
mseep_cleanuri_url_shorterner-0.1.1.dist-info/licenses/LICENSE
mseep_cleanuri_url_shorterner-0.1.1.dist-info/METADATA
mseep_cleanuri_url_shorterner-0.1.1.dist-info/WHEEL
mseep_cleanuri_url_shorterner-0.1.1.dist-info/entry_points.txt
mseep_cleanuri_url_shorterner-0.1.1.dist-info/top_level.txt
mseep_cleanuri_url_shorterner-0.1.1.dist-info/RECORD
